circleblock/__init__.py
circleblock/changer.py
circleblock/circleblock_cli.py
circleblock/watcher.py
CircleBlock-1.1.0.dist-info/LICENSE
CircleBlock-1.1.0.dist-info/METADATA
CircleBlock-1.1.0.dist-info/WHEEL
CircleBlock-1.1.0.dist-info/entry_points.txt
CircleBlock-1.1.0.dist-info/top_level.txt
CircleBlock-1.1.0.dist-info/RECORD
